{
  "Id": 350000200,
  "Name": "이상 · 크라운리스",
  "Desc": "운릉 협곡 밖에서 나타난 의음종 잔상, 성질이 사납고 호전적이며 또한 매우 공격적이다. 더 많은 정보는 아직 보충할 필요가 있다. 위험도가 노도급에 속하는 것으로 알려져 있다",
  "DescOpen": "해당 적의 <color=Dark>인멸 피해</color> <color=HighlightB>저항이 증가한다</color>. \n갑자기 나타난 신비로운 무음구역와 함께 운릉 협곡 밖에서 태어난 의음종 잔상이다. 체내에 수많은 인간 주파수가 융합되어 있음을 감지하고, 승리에 대한 흥분과 갈망, 전장에서의 죽음에 대한 공포와 원망… 뼈와 피 속에 억눌려 있던 인류의 투혼은 자신에 대한 시련으로 변모했다. 이것의 존재는 어두운 곳에 칩거하는 적으로부터 파견된 병졸이며, 끝없는 전화의 전조이기도 하다",
  "Rarity": 3,
  "Element": 6,
  "ElementArray": [
    6
  ],
  "Icon": "/Game/Aki/UI/UIResources/Common/Image/IconMonsterHead/T_IconMonsterHead_SG_9991_UI.T_IconMonsterHead_SG_9991_UI",
  "Echo": 6010042,
  "BaseStats": {},
  "Stats": {}
}