{
  "Id": 6000189,
  "Code": "T01-",
  "Name": "하이와티아",
  "Type": "",
  "Intensity": "",
  "Place": "",
  "Icon": "/Game/Aki/UI/UIResources/Common/Image/IconMonsterHead/T_IconMonsterHead_34021_UI.T_IconMonsterHead_34021_UI",
  "Skill": {
    "Desc": "에코 어빌리티를 사용하여 하이와티아를 소환한 후, 공중에서 레이저를 발사하여 적에게 {0}의 회절 피해를 10단 입힌다.\n이후 {1}초 내에 자신이 반주 스킬 발동 시, 다음번 변주 스킬로 등장한 캐릭터의 전체 속성 피해 보너스를 {2} 증가시키고, {3}초간 지속된다.\n스킬 쿨타임: {4}초",
    "SimpleDesc": "하이와티아를 소환하여 적에게 회절 피해를 입히고 다음번 변주 스킬로 등장한 캐릭터의 전체 속성 피해를 증가시킨다",
    "Param": [
      [
        "15.20%",
        "15",
        "10.00%",
        "15",
        "20"
      ],
      [
        "18.24%",
        "15",
        "10.00%",
        "15",
        "20"
      ],
      [
        "21.28%",
        "15",
        "10.00%",
        "15",
        "20"
      ],
      [
        "24.32%",
        "15",
        "10.00%",
        "15",
        "20"
      ],
      [
        "27.36%",
        "15",
        "10.00%",
        "15",
        "20"
      ]
    ],
    "Icon": "/Game/Aki/UI/UIResources/Common/Image/MstSkill/T_MstSkil_34021_UI.T_MstSkil_34021_UI",
    "Damage": {
      "28003601": {
        "Element": 5,
        "RelatedProperty": "공격력",
        "Type": 5,
        "RateLv": [
          1520,
          1824,
          2128,
          2432,
          2736
        ],
        "Energy": 3,
        "ElementPower": 0,
        "HardnessLv": 10000,
        "ToughLv": 1520
      }
    }
  },
  "Group": {
    "24": {
      "Id": 24,
      "Name": "역광 속 눈부신 서약",
      "Icon": "/Game/Aki/UI/UIResources/Common/Image/IconElementAttri/T_IconElementAttriLightWeakness.T_IconElementAttriLightWeakness",
      "Color": "FFFFFF00",
      "Set": {
        "2": {
          "Desc": "회절 피해가 {0} 증가된다",
          "Param": [
            "10%"
          ]
        },
        "5": {
          "Desc": "캐릭터가 반주 스킬 발동 후, 다음번 변주 스킬로 등장하는 캐릭터의 공격력이 {0} 증가된다. 조화도 파괴 증폭 1pt마다 추가로 공격력을 {1} 증가시키고, 최대 {2}까지 증가시키며, {3}초간 지속된다. 다른 캐릭터로 교체 시 해당 효과는 즉시 종료된다",
          "Param": [
            "15%",
            "0.3%",
            "15%",
            "15"
          ]
        }
      }
    },
    "26": {
      "Id": 26,
      "Name": "흐르는 금빛 속 진리의 답",
      "Icon": "/Game/Aki/UI/UIResources/Common/Image/IconElementAttri/T_IconElementAttriAttackWeakness.T_IconElementAttriAttackWeakness",
      "Color": "FFFFFF00",
      "Set": {
        "2": {
          "Desc": "회절 피해가 {0} 증가된다",
          "Param": [
            "10%"
          ]
        },
        "5": {
          "Desc": "캐릭터가 일반 공격으로 피해를 입힐 시, 자신의 회절 피해가 {0} 증가되고, 해당 효과는 {1}스택 중첩이 가능하며, {2}초간 지속된다. {1}스택 중첩 시, 공명 해방을 발동하면 일반 공격 피해 보너스가 {3} 증가된다",
          "Param": [
            "10%",
            "3",
            "5",
            "40%"
          ]
        }
      }
    }
  },
  "Rarity": [
    2,
    3,
    4,
    5
  ],
  "IntensityCode": 2,
  "MonsterInfo": 340000210
}