{
  "Id": 6000120,
  "Code": "H56-",
  "Name": "코로사우루스",
  "Type": "",
  "Intensity": "",
  "Place": "",
  "Icon": "/Game/Aki/UI/UIResources/Common/Image/IconMonsterHead/T_IconMonsterHead_32044_UI.T_IconMonsterHead_32044_UI",
  "Skill": {
    "Desc": "에코 어빌리티를 사용하여 코로사우루스를 소환하고 적에게 {0}의 용융 피해를 입힌다.\n메인 슬롯에 해당 에코 어빌리티를 장착 시, 자신의 용융 피해 보너스가 {1} 증가되고, 에코 어빌리티 피해 보너스가 {2} 증가된다.\n스킬 쿨타임: {3}초",
    "SimpleDesc": "코로사우루스를 소환하여 용융 피해를 입힌다.\n메인 슬롯에 장착 시, 자신의 용융 피해와 에코 어빌리티 피해를 증가시킨다",
    "Param": [
      [
        "152.00%",
        "12.00%",
        "20.00%",
        "20"
      ],
      [
        "182.40%",
        "12.00%",
        "20.00%",
        "20"
      ],
      [
        "212.80%",
        "12.00%",
        "20.00%",
        "20"
      ],
      [
        "243.20%",
        "12.00%",
        "20.00%",
        "20"
      ],
      [
        "273.60%",
        "12.00%",
        "20.00%",
        "20"
      ]
    ],
    "Icon": "/Game/Aki/UI/UIResources/Common/Image/MstSkill/T_MstSkil_32044_UI.T_MstSkil_32044_UI",
    "Damage": {
      "20009801": {
        "Element": 2,
        "RelatedProperty": "공격력",
        "Type": 5,
        "RateLv": [
          15200,
          18240,
          21280,
          24320,
          27360
        ],
        "Energy": 380,
        "ElementPower": 0,
        "HardnessLv": 10000,
        "ToughLv": 15200
      }
    }
  },
  "Group": {
    "18": {
      "Id": 18,
      "Name": "울부짖는 늑대의 불꽃",
      "Icon": "/Game/Aki/UI/UIResources/Common/Image/IconElementAttri/T_IconElementAttriFireUltimateSkill.T_IconElementAttriFireUltimateSkill",
      "Color": "FFFFFF00",
      "Set": {
        "2": {
          "Desc": "용융 피해가 {0} 증가된다",
          "Param": [
            "10%"
          ]
        },
        "5": {
          "Desc": "공명 해방 발동 시, 파티 내 캐릭터의 용융 피해가 {0} 증가되고, 자신의 공명 해방 피해가 {1} 증가되며, {2}초간 지속된다",
          "Param": [
            "15%",
            "20%",
            "35"
          ]
        }
      }
    },
    "22": {
      "Id": 22,
      "Name": "불타는 깃털을 펼친 사냥꾼의 그림자",
      "Icon": "/Game/Aki/UI/UIResources/Common/Image/IconElementAttri/T_IconElementAttriFireA.T_IconElementAttriFireA",
      "Color": "FFFFFF00",
      "Set": {
        "3": {
          "Desc": "캐릭터가 에코 어빌리티 피해를 입힐 시, 강공격 피해의 크리티컬이 {0} 증가되고 {1}초간 지속된다. 강공격 피해를 입힐 시, 에코 어빌리티 피해의 크리티컬이 {2} 증가되고 {3}초간 지속된다. 두 가지 효과를 동시에 보유 시, 자신의 용융 피해가 {4} 증가된다",
          "Param": [
            "20%",
            "6",
            "20%",
            "6",
            "16%"
          ]
        }
      }
    }
  },
  "Rarity": [
    2,
    3,
    4,
    5
  ],
  "IntensityCode": 1,
  "MonsterInfo": 320000440
}